{
  "status": "researched",
  "summary": "Task 26 memory monitoring is fully operational; systemd-oomd explicitly warns 'No swap; memory pressure usage will be degraded' confirming swap is needed; existing implementation plan remains valid without revision.",
  "artifacts": [
    {
      "type": "research",
      "path": "specs/25_configure_swap_space_nixos/reports/research-002.md",
      "summary": "Additional research analyzing Task 26 implementation to inform swap configuration approach"
    }
  ],
  "metadata": {
    "session_id": "sess_1770842766_85fdfd",
    "agent_type": "nix-research-agent",
    "duration_seconds": 180,
    "delegation_depth": 1,
    "delegation_path": ["orchestrator", "research", "nix-research-agent"],
    "findings_count": 6
  }
}
